lasotuvi/AmDuong.py
lasotuvi/App.py
lasotuvi/DiaBan.py
lasotuvi/Lich_EPHEM.py
lasotuvi/Lich_HND.py
lasotuvi/Sao.py
lasotuvi/ThienBan.py
lasotuvi/__init__.py
lasotuvi-0.1.2.dist-info/METADATA
lasotuvi-0.1.2.dist-info/RECORD
lasotuvi-0.1.2.dist-info/WHEEL
lasotuvi-0.1.2.dist-info/top_level.txt
